{"success":true,"meetings":[{"id":66,"event_id":"2156","meeting_date":"2025-12-16","meeting_type":"regular","legistar_url":null,"agenda_url":"https://legistar.granicus.com/lausd/meetings/2025/12/2156_A_Board_of_Education_25-12-16_ORDER_OF_BUSINESS.pdf","minutes_url":null,"video_url":null,"agenda_item_count":64,"vote_count":33,"non_voted_count":31,"first_reading_count":0},{"id":65,"event_id":"2151","meeting_date":"2025-11-18","meeting_type":"regular","legistar_url":null,"agenda_url":"https://legistar.granicus.com/lausd/meetings/2025/11/2151_A_Board_of_Education_25-11-18_ORDER_OF_BUSINESS.pdf","minutes_url":null,"video_url":"https://lausdca.new.swagit.com/events/43400","agenda_item_count":53,"vote_count":32,"non_voted_count":21,"first_reading_count":0},{"id":64,"event_id":"2152","meeting_date":"2025-11-17","meeting_type":"regular","legistar_url":null,"agenda_url":"https://legistar.granicus.com/lausd/meetings/2025/11/2152_A_Board_of_Education_25-11-17_ORDER_OF_BUSINESS.pdf","minutes_url":null,"video_url":"https://lausdca.new.swagit.com/videos/361007?place=holder","agenda_item_count":29,"vote_count":26,"non_voted_count":3,"first_reading_count":0},{"id":63,"event_id":"2127","meeting_date":"2025-09-16","meeting_type":"regular","legistar_url":null,"agenda_url":"https://legistar.granicus.com/lausd/meetings/2025/9/2127_A_Board_of_Education_25-09-16_ORDER_OF_BUSINESS.pdf","minutes_url":null,"video_url":"https://lausdca.new.swagit.com/events/42313","agenda_item_count":53,"vote_count":19,"non_voted_count":34,"first_reading_count":0},{"id":62,"event_id":"2124","meeting_date":"2025-08-26","meeting_type":"regular","legistar_url":null,"agenda_url":"https://legistar.granicus.com/lausd/meetings/2025/8/2124_A_Board_of_Education_25-08-26_ORDER_OF_BUSINESS.pdf","minutes_url":null,"video_url":null,"agenda_item_count":40,"vote_count":0,"non_voted_count":40,"first_reading_count":0},{"id":61,"event_id":"2119","meeting_date":"2025-06-24","meeting_type":"regular","legistar_url":null,"agenda_url":"https://legistar.granicus.com/lausd/meetings/2025/6/2119_A_Board_of_Education_25-06-24_ORDER_OF_BUSINESS.pdf","minutes_url":null,"video_url":null,"agenda_item_count":27,"vote_count":13,"non_voted_count":14,"first_reading_count":0},{"id":60,"event_id":"2118","meeting_date":"2025-06-17","meeting_type":"regular","legistar_url":null,"agenda_url":null,"minutes_url":null,"video_url":null,"agenda_item_count":22,"vote_count":1,"non_voted_count":21,"first_reading_count":0},{"id":59,"event_id":"2111","meeting_date":"2025-06-03","meeting_type":"regular","legistar_url":null,"agenda_url":"https://legistar.granicus.com/lausd/meetings/2025/6/2111_A_Board_of_Education_25-06-03_ORDER_OF_BUSINESS.pdf","minutes_url":null,"video_url":null,"agenda_item_count":55,"vote_count":35,"non_voted_count":20,"first_reading_count":0},{"id":58,"event_id":"2090","meeting_date":"2025-04-08","meeting_type":"regular","legistar_url":null,"agenda_url":null,"minutes_url":null,"video_url":"https://lausd.granicus.com/MediaPlayer.php?view_id=4&clip_id=4604","agenda_item_count":51,"vote_count":16,"non_voted_count":35,"first_reading_count":0},{"id":57,"event_id":"2080","meeting_date":"2025-03-11","meeting_type":"regular","legistar_url":null,"agenda_url":"https://legistar.granicus.com/lausd/meetings/2025/3/2080_A_Board_of_Education_25-03-11_ORDER_OF_BUSINESS.pdf","minutes_url":null,"video_url":"https://lausd.granicus.com/MediaPlayer.php?view_id=4&clip_id=4589","agenda_item_count":49,"vote_count":0,"non_voted_count":49,"first_reading_count":0},{"id":56,"event_id":"2069","meeting_date":"2025-02-11","meeting_type":"regular","legistar_url":null,"agenda_url":null,"minutes_url":null,"video_url":"https://lausd.granicus.com/MediaPlayer.php?view_id=4&clip_id=4575","agenda_item_count":124,"vote_count":1,"non_voted_count":123,"first_reading_count":0},{"id":55,"event_id":"2074","meeting_date":"2025-01-30","meeting_type":"regular","legistar_url":null,"agenda_url":null,"minutes_url":null,"video_url":null,"agenda_item_count":17,"vote_count":0,"non_voted_count":17,"first_reading_count":0},{"id":54,"event_id":"2068","meeting_date":"2025-01-22","meeting_type":"regular","legistar_url":null,"agenda_url":null,"minutes_url":null,"video_url":null,"agenda_item_count":16,"vote_count":0,"non_voted_count":16,"first_reading_count":0},{"id":53,"event_id":"2058","meeting_date":"2025-01-14","meeting_type":"regular","legistar_url":null,"agenda_url":null,"minutes_url":null,"video_url":"https://lausd.granicus.com/MediaPlayer.php?view_id=4&clip_id=4560","agenda_item_count":51,"vote_count":0,"non_voted_count":51,"first_reading_count":0},{"id":52,"event_id":"FM-2024-11-19","meeting_date":"2024-11-19","meeting_type":"regular","legistar_url":null,"agenda_url":null,"minutes_url":null,"video_url":"https://lausd.granicus.com/MediaPlayer.php?view_id=4&clip_id=4539","agenda_item_count":7,"vote_count":7,"non_voted_count":0,"first_reading_count":0},{"id":51,"event_id":"FM-2024-10-22","meeting_date":"2024-10-22","meeting_type":"regular","legistar_url":null,"agenda_url":null,"minutes_url":null,"video_url":"https://lausd.granicus.com/MediaPlayer.php?view_id=4&clip_id=4516","agenda_item_count":3,"vote_count":3,"non_voted_count":0,"first_reading_count":0},{"id":50,"event_id":"FM-2024-09-10","meeting_date":"2024-09-10","meeting_type":"regular","legistar_url":null,"agenda_url":null,"minutes_url":null,"video_url":"https://lausd.granicus.com/MediaPlayer.php?view_id=4&clip_id=4491","agenda_item_count":7,"vote_count":7,"non_voted_count":0,"first_reading_count":0},{"id":49,"event_id":"FM-2024-06-25","meeting_date":"2024-06-25","meeting_type":"regular","legistar_url":null,"agenda_url":null,"minutes_url":null,"video_url":"https://lausd.granicus.com/MediaPlayer.php?view_id=4&clip_id=4462","agenda_item_count":2,"vote_count":2,"non_voted_count":0,"first_reading_count":0},{"id":48,"event_id":"FM-2024-06-18","meeting_date":"2024-06-18","meeting_type":"regular","legistar_url":null,"agenda_url":null,"minutes_url":null,"video_url":"https://lausd.granicus.com/MediaPlayer.php?view_id=4&clip_id=4455","agenda_item_count":6,"vote_count":6,"non_voted_count":0,"first_reading_count":0},{"id":47,"event_id":"FM-2024-06-04","meeting_date":"2024-06-04","meeting_type":"regular","legistar_url":null,"agenda_url":null,"minutes_url":null,"video_url":"https://lausd.granicus.com/MediaPlayer.php?view_id=4&clip_id=4449","agenda_item_count":2,"vote_count":2,"non_voted_count":0,"first_reading_count":0},{"id":46,"event_id":"FM-2024-05-07","meeting_date":"2024-05-07","meeting_type":"regular","legistar_url":null,"agenda_url":null,"minutes_url":null,"video_url":"https://lausd.granicus.com/MediaPlayer.php?view_id=4&clip_id=4432","agenda_item_count":3,"vote_count":3,"non_voted_count":0,"first_reading_count":0},{"id":45,"event_id":"FM-2024-03-12","meeting_date":"2024-03-12","meeting_type":"regular","legistar_url":null,"agenda_url":null,"minutes_url":null,"video_url":"https://lausd.granicus.com/MediaPlayer.php?view_id=4&clip_id=4399","agenda_item_count":3,"vote_count":3,"non_voted_count":0,"first_reading_count":0},{"id":44,"event_id":"FM-2024-02-13","meeting_date":"2024-02-13","meeting_type":"regular","legistar_url":null,"agenda_url":null,"minutes_url":null,"video_url":"https://lausd.granicus.com/MediaPlayer.php?view_id=4&clip_id=4390","agenda_item_count":1,"vote_count":1,"non_voted_count":0,"first_reading_count":0},{"id":43,"event_id":"FM-2024-01-23","meeting_date":"2024-01-23","meeting_type":"regular","legistar_url":null,"agenda_url":null,"minutes_url":null,"video_url":"https://lausd.granicus.com/MediaPlayer.php?view_id=4&clip_id=4378","agenda_item_count":3,"vote_count":3,"non_voted_count":0,"first_reading_count":0},{"id":42,"event_id":"FM-2023-12-12","meeting_date":"2023-12-12","meeting_type":"regular","legistar_url":null,"agenda_url":null,"minutes_url":null,"video_url":"https://lausd.granicus.com/MediaPlayer.php?view_id=4&clip_id=4367","agenda_item_count":1,"vote_count":1,"non_voted_count":0,"first_reading_count":0},{"id":41,"event_id":"FM-2023-11-14","meeting_date":"2023-11-14","meeting_type":"regular","legistar_url":null,"agenda_url":null,"minutes_url":null,"video_url":"https://lausd.granicus.com/MediaPlayer.php?view_id=4&clip_id=4349","agenda_item_count":6,"vote_count":6,"non_voted_count":0,"first_reading_count":0},{"id":40,"event_id":"FM-2023-10-17","meeting_date":"2023-10-17","meeting_type":"regular","legistar_url":null,"agenda_url":null,"minutes_url":null,"video_url":"https://lausd.granicus.com/MediaPlayer.php?view_id=4&clip_id=4329","agenda_item_count":4,"vote_count":4,"non_voted_count":0,"first_reading_count":0},{"id":39,"event_id":"FM-2023-09-26","meeting_date":"2023-09-26","meeting_type":"regular","legistar_url":null,"agenda_url":null,"minutes_url":null,"video_url":"https://lausd.granicus.com/MediaPlayer.php?view_id=4&clip_id=4325","agenda_item_count":1,"vote_count":1,"non_voted_count":0,"first_reading_count":0},{"id":38,"event_id":"FM-2023-09-12","meeting_date":"2023-09-12","meeting_type":"regular","legistar_url":null,"agenda_url":null,"minutes_url":null,"video_url":"https://lausd.granicus.com/MediaPlayer.php?view_id=4&clip_id=4310","agenda_item_count":3,"vote_count":3,"non_voted_count":0,"first_reading_count":0},{"id":37,"event_id":"FM-2023-08-22","meeting_date":"2023-08-22","meeting_type":"regular","legistar_url":null,"agenda_url":null,"minutes_url":null,"video_url":"https://lausd.granicus.com/MediaPlayer.php?view_id=4&clip_id=4300","agenda_item_count":4,"vote_count":4,"non_voted_count":0,"first_reading_count":0},{"id":36,"event_id":"FM-2023-06-13","meeting_date":"2023-06-13","meeting_type":"regular","legistar_url":null,"agenda_url":null,"minutes_url":null,"video_url":"https://lausd.granicus.com/MediaPlayer.php?view_id=4&clip_id=4286","agenda_item_count":2,"vote_count":2,"non_voted_count":0,"first_reading_count":0},{"id":35,"event_id":"FM-2023-05-23","meeting_date":"2023-05-23","meeting_type":"regular","legistar_url":null,"agenda_url":null,"minutes_url":null,"video_url":"https://lausd.granicus.com/MediaPlayer.php?view_id=4&clip_id=4267","agenda_item_count":3,"vote_count":3,"non_voted_count":0,"first_reading_count":0},{"id":34,"event_id":"FM-2023-05-09","meeting_date":"2023-05-09","meeting_type":"regular","legistar_url":null,"agenda_url":null,"minutes_url":null,"video_url":"https://lausd.granicus.com/MediaPlayer.php?view_id=4&clip_id=4257","agenda_item_count":1,"vote_count":1,"non_voted_count":0,"first_reading_count":0},{"id":33,"event_id":"FM-2023-04-18","meeting_date":"2023-04-18","meeting_type":"regular","legistar_url":null,"agenda_url":null,"minutes_url":null,"video_url":"https://lausd.granicus.com/MediaPlayer.php?view_id=4&clip_id=4233","agenda_item_count":2,"vote_count":2,"non_voted_count":0,"first_reading_count":0},{"id":32,"event_id":"FM-2023-03-07","meeting_date":"2023-03-07","meeting_type":"regular","legistar_url":null,"agenda_url":null,"minutes_url":null,"video_url":"https://lausd.granicus.com/MediaPlayer.php?view_id=4&clip_id=4199","agenda_item_count":1,"vote_count":1,"non_voted_count":0,"first_reading_count":0},{"id":31,"event_id":"FM-2023-01-17","meeting_date":"2023-01-17","meeting_type":"regular","legistar_url":null,"agenda_url":null,"minutes_url":null,"video_url":"https://lausd.granicus.com/MediaPlayer.php?view_id=4&clip_id=4166","agenda_item_count":2,"vote_count":2,"non_voted_count":0,"first_reading_count":0},{"id":30,"event_id":"FM-2022-09-27","meeting_date":"2022-09-27","meeting_type":"regular","legistar_url":null,"agenda_url":null,"minutes_url":null,"video_url":"https://lausd.granicus.com/MediaPlayer.php?view_id=4&clip_id=4098","agenda_item_count":1,"vote_count":1,"non_voted_count":0,"first_reading_count":0},{"id":29,"event_id":"FM-2022-08-30","meeting_date":"2022-08-30","meeting_type":"regular","legistar_url":null,"agenda_url":null,"minutes_url":null,"video_url":"https://lausd.granicus.com/MediaPlayer.php?view_id=4&clip_id=4073","agenda_item_count":1,"vote_count":1,"non_voted_count":0,"first_reading_count":0},{"id":28,"event_id":"FM-2022-06-14","meeting_date":"2022-06-14","meeting_type":"regular","legistar_url":null,"agenda_url":null,"minutes_url":null,"video_url":"https://lausd.granicus.com/MediaPlayer.php?view_id=4&clip_id=4048","agenda_item_count":1,"vote_count":1,"non_voted_count":0,"first_reading_count":0},{"id":27,"event_id":"FM-2022-05-10","meeting_date":"2022-05-10","meeting_type":"regular","legistar_url":null,"agenda_url":null,"minutes_url":null,"video_url":"https://lausd.granicus.com/MediaPlayer.php?view_id=4&clip_id=4020","agenda_item_count":3,"vote_count":3,"non_voted_count":0,"first_reading_count":0},{"id":26,"event_id":"FM-2022-04-05","meeting_date":"2022-04-05","meeting_type":"regular","legistar_url":null,"agenda_url":null,"minutes_url":null,"video_url":"https://lausd.granicus.com/MediaPlayer.php?view_id=4&clip_id=4005","agenda_item_count":2,"vote_count":2,"non_voted_count":0,"first_reading_count":0},{"id":25,"event_id":"FM-2022-03-08","meeting_date":"2022-03-08","meeting_type":"regular","legistar_url":null,"agenda_url":null,"minutes_url":null,"video_url":"https://lausd.granicus.com/MediaPlayer.php?view_id=4&clip_id=3987","agenda_item_count":2,"vote_count":2,"non_voted_count":0,"first_reading_count":0},{"id":24,"event_id":"FM-2022-02-08","meeting_date":"2022-02-08","meeting_type":"regular","legistar_url":null,"agenda_url":null,"minutes_url":null,"video_url":"https://lausd.granicus.com/MediaPlayer.php?view_id=4&clip_id=3973","agenda_item_count":6,"vote_count":6,"non_voted_count":0,"first_reading_count":0},{"id":23,"event_id":"FM-2022-01-25","meeting_date":"2022-01-25","meeting_type":"regular","legistar_url":null,"agenda_url":null,"minutes_url":null,"video_url":"https://lausd.granicus.com/MediaPlayer.php?view_id=4&clip_id=3962","agenda_item_count":5,"vote_count":5,"non_voted_count":0,"first_reading_count":0},{"id":22,"event_id":"FM-2021-12-07","meeting_date":"2021-12-07","meeting_type":"regular","legistar_url":null,"agenda_url":null,"minutes_url":null,"video_url":"https://lausd.granicus.com/MediaPlayer.php?view_id=4&clip_id=3927","agenda_item_count":1,"vote_count":1,"non_voted_count":0,"first_reading_count":0},{"id":21,"event_id":"FM-2021-11-09","meeting_date":"2021-11-09","meeting_type":"regular","legistar_url":null,"agenda_url":null,"minutes_url":null,"video_url":"https://lausd.granicus.com/MediaPlayer.php?view_id=4&clip_id=3895","agenda_item_count":1,"vote_count":1,"non_voted_count":0,"first_reading_count":0},{"id":20,"event_id":"FM-2021-10-26","meeting_date":"2021-10-26","meeting_type":"regular","legistar_url":null,"agenda_url":null,"minutes_url":null,"video_url":"https://lausd.granicus.com/MediaPlayer.php?view_id=4&clip_id=3886","agenda_item_count":2,"vote_count":2,"non_voted_count":0,"first_reading_count":0},{"id":19,"event_id":"FM-2021-10-12","meeting_date":"2021-10-12","meeting_type":"regular","legistar_url":null,"agenda_url":null,"minutes_url":null,"video_url":"https://lausd.granicus.com/MediaPlayer.php?view_id=4&clip_id=3869","agenda_item_count":1,"vote_count":1,"non_voted_count":0,"first_reading_count":0},{"id":18,"event_id":"FM-2021-09-28","meeting_date":"2021-09-28","meeting_type":"regular","legistar_url":null,"agenda_url":null,"minutes_url":null,"video_url":"https://lausd.granicus.com/MediaPlayer.php?view_id=4&clip_id=4041","agenda_item_count":1,"vote_count":1,"non_voted_count":0,"first_reading_count":0},{"id":17,"event_id":"FM-2021-09-14","meeting_date":"2021-09-14","meeting_type":"regular","legistar_url":null,"agenda_url":null,"minutes_url":null,"video_url":"https://lausd.granicus.com/MediaPlayer.php?view_id=4&clip_id=3848","agenda_item_count":6,"vote_count":6,"non_voted_count":0,"first_reading_count":0},{"id":16,"event_id":"FM-2021-08-24","meeting_date":"2021-08-24","meeting_type":"regular","legistar_url":null,"agenda_url":null,"minutes_url":null,"video_url":"https://lausd.granicus.com/MediaPlayer.php?view_id=4&clip_id=3830","agenda_item_count":3,"vote_count":3,"non_voted_count":0,"first_reading_count":0},{"id":15,"event_id":"FM-2021-07-13","meeting_date":"2021-07-13","meeting_type":"regular","legistar_url":null,"agenda_url":null,"minutes_url":null,"video_url":"https://lausd.granicus.com/MediaPlayer.php?view_id=4&clip_id=3815","agenda_item_count":4,"vote_count":4,"non_voted_count":0,"first_reading_count":0},{"id":14,"event_id":"FM-2021-06-22","meeting_date":"2021-06-22","meeting_type":"regular","legistar_url":null,"agenda_url":null,"minutes_url":null,"video_url":"https://lausd.granicus.com/MediaPlayer.php?view_id=4&clip_id=3809","agenda_item_count":2,"vote_count":2,"non_voted_count":0,"first_reading_count":0},{"id":13,"event_id":"FM-2021-06-15","meeting_date":"2021-06-15","meeting_type":"regular","legistar_url":null,"agenda_url":null,"minutes_url":null,"video_url":"https://lausd.granicus.com/MediaPlayer.php?view_id=4&clip_id=3798","agenda_item_count":1,"vote_count":1,"non_voted_count":0,"first_reading_count":0},{"id":12,"event_id":"FM-2021-06-08","meeting_date":"2021-06-08","meeting_type":"regular","legistar_url":null,"agenda_url":null,"minutes_url":null,"video_url":"https://lausd.granicus.com/MediaPlayer.php?view_id=4&clip_id=3796","agenda_item_count":1,"vote_count":1,"non_voted_count":0,"first_reading_count":0},{"id":11,"event_id":"FM-2021-05-18","meeting_date":"2021-05-18","meeting_type":"regular","legistar_url":null,"agenda_url":null,"minutes_url":null,"video_url":"https://lausd.granicus.com/MediaPlayer.php?view_id=4&clip_id=3782","agenda_item_count":1,"vote_count":1,"non_voted_count":0,"first_reading_count":0},{"id":10,"event_id":"FM-2021-05-11","meeting_date":"2021-05-11","meeting_type":"regular","legistar_url":null,"agenda_url":null,"minutes_url":null,"video_url":"https://lausd.granicus.com/MediaPlayer.php?view_id=4&clip_id=3779","agenda_item_count":7,"vote_count":7,"non_voted_count":0,"first_reading_count":0},{"id":9,"event_id":"FM-2021-04-14","meeting_date":"2021-04-14","meeting_type":"regular","legistar_url":null,"agenda_url":null,"minutes_url":null,"video_url":"https://lausd.granicus.com/MediaPlayer.php?view_id=4&clip_id=3751","agenda_item_count":6,"vote_count":6,"non_voted_count":0,"first_reading_count":0},{"id":8,"event_id":"FM-2021-03-09","meeting_date":"2021-03-09","meeting_type":"regular","legistar_url":null,"agenda_url":null,"minutes_url":null,"video_url":"https://lausd.granicus.com/MediaPlayer.php?view_id=4&clip_id=3739","agenda_item_count":3,"vote_count":3,"non_voted_count":0,"first_reading_count":0},{"id":7,"event_id":"FM-2021-02-23","meeting_date":"2021-02-23","meeting_type":"regular","legistar_url":null,"agenda_url":null,"minutes_url":null,"video_url":"https://lausd.granicus.com/MediaPlayer.php?view_id=4&clip_id=3734","agenda_item_count":1,"vote_count":1,"non_voted_count":0,"first_reading_count":0},{"id":6,"event_id":"FM-2021-02-09","meeting_date":"2021-02-09","meeting_type":"regular","legistar_url":null,"agenda_url":null,"minutes_url":null,"video_url":"https://lausd.granicus.com/MediaPlayer.php?view_id=4&clip_id=3728","agenda_item_count":3,"vote_count":3,"non_voted_count":0,"first_reading_count":0},{"id":5,"event_id":"FM-2021-01-12","meeting_date":"2021-01-12","meeting_type":"regular","legistar_url":null,"agenda_url":null,"minutes_url":null,"video_url":"https://lausd.granicus.com/MediaPlayer.php?view_id=4&clip_id=3718","agenda_item_count":1,"vote_count":1,"non_voted_count":0,"first_reading_count":0},{"id":4,"event_id":"FM-2020-03-10","meeting_date":"2020-03-10","meeting_type":"regular","legistar_url":null,"agenda_url":"https://lausd.granicus.com/AgendaViewer.php?view_id=4&clip_id=3615","minutes_url":null,"video_url":"https://lausd.granicus.com/MediaPlayer.php?view_id=4&clip_id=3615","agenda_item_count":4,"vote_count":4,"non_voted_count":0,"first_reading_count":0},{"id":3,"event_id":"FM-2020-02-10","meeting_date":"2020-02-10","meeting_type":"regular","legistar_url":null,"agenda_url":null,"minutes_url":null,"video_url":null,"agenda_item_count":1,"vote_count":1,"non_voted_count":0,"first_reading_count":0},{"id":2,"event_id":"FM-2020-02-04","meeting_date":"2020-02-04","meeting_type":"regular","legistar_url":null,"agenda_url":"https://lausd.granicus.com/AgendaViewer.php?view_id=4&clip_id=3601","minutes_url":null,"video_url":"https://lausd.granicus.com/MediaPlayer.php?view_id=4&clip_id=3601","agenda_item_count":5,"vote_count":5,"non_voted_count":0,"first_reading_count":0},{"id":1,"event_id":"FM-2020-01-14","meeting_date":"2020-01-14","meeting_type":"regular","legistar_url":null,"agenda_url":"https://lausd.granicus.com/AgendaViewer.php?view_id=4&clip_id=3591","minutes_url":null,"video_url":"https://lausd.granicus.com/MediaPlayer.php?view_id=4&clip_id=3591","agenda_item_count":4,"vote_count":4,"non_voted_count":0,"first_reading_count":0}],"available_years":[2025,2024,2023,2022,2021,2020]}